[{"_id:": 101297033, "nome:": "Dedo retrátil - 0183-01", "descricao": "Dedo retrátil", "atributos": "Furo Ø 4 mm", "linha": "Plataforma", "familia": "Dedo retrátil", "aplicacao": "Sem fim alimentação", "material": "Aço ABNT 1045", "tratamento": "Indução", "dureza": "mínimo 52 HRc", "acabamento": "Oleado", "pesoLiquido(Kg)": "0,2420", "pesoBruto(Kg)": "0,2580"},,{"_id:": 100415797, "nome:": "Engrenagem - 3462-00", "descricao": "Engrenagem", "atributos": "Z13 P 41,4 mm", "linha": "Colheitadeira", "familia": "Engrenagem", "aplicacao": "Elevador de palha", "material": "Ferro fundido cinzento GG25", "tratamento": "Indução", "dureza": "40 a 50 HRc", "acabamento": "Pintura verde", "pesoLiquido(Kg)": "3,7250", "pesoBruto(Kg)": "3,7250"},{"_id:": 101297491, "nome:": "Junção da barra seccionada - 6200-99", "descricao": "Junção da barra seccionada", "atributos": "Sistema 4\"", "observacoes": "", "linha": "Plataforma", "familia": "Junção da barra seccionada", "aplicacao": "Sistema de corte curto", "material": "Barra reforço: Aço ABNT 1070", "tratamento": "Tempera", "dureza": "47 a 52 HRc", "acabamento": "Envernizado", "pesoLiquido(Kg)": "0,3500", "pesoBruto(Kg)": "0,3500"},{"_id:": 101281421, "nome:": "Cubo - 0393-00", "descricao": "Cubo", "linha": "Colheitadeira", "familia": "Cubo", "aplicacao": "Saca palha", "material": "Ferro fundido cinzento GG25", "acabamento": "Oleado", "pesoLiquido(Kg)": "0,4350", "pesoBruto(Kg)": "0,4450"},,{"_id:": 101286655, "nome:": "Cabeça da Navalha - 0672-02", "descricao": "Cabeça da Navalha", "linha": "Plataforma", "familia": "Cabeça da navalha", "aplicacao": "Sistema de corte", "material": "Ferro fundido nodular GGG40, haste: aço ABNT 1045", "acabamento": "Pintura amarela", "pesoLiquido(Kg)": "0,9000", "pesoBruto(Kg)": "0,9000"},{"_id:": 101297095, "nome:": "Dedo retrátil - 0278-01", "descricao": "Dedo retrátil", "atributos": "Furo Ø 4 mm", "observacoes": "Pino R", "linha": "Plataforma", "familia": "Dedo retrátil", "aplicacao": "Sem fim alimentação", "material": "Aço ABNT 1045", "tratamento": "Indução", "dureza": "mínimo 52 HRc", "acabamento": "Oleado", "pesoLiquido(Kg)": "0,4160", "pesoBruto(Kg)": "0,4170"},{"_id:": 100917932, "nome:": "Cabeça da Navalha - 3964-00", "descricao": "Cabeça da Navalha", "atributos": "Bloco com rosca M16, terminal temperado", "linha": "Plataforma", "familia": "Cabeça da navalha", "aplicacao": "Sistema de corte", "material": "Aço ABNT 1045, haste: Aço ABNT 1020", "tratamento": "Indução", "acabamento": "Pintura preta", "pesoLiquido(Kg)": "2,2560", "pesoBruto(Kg)": "2,8800"},{"_id:": 101279633, "nome:": "Engrenagem - 0164-00", "descricao": "Engrenagem", "atributos": "Z33 P 1\"", "linha": "Colheitadeira", "familia": "Engrenagem", "aplicacao": "Reversor", "material": "Aço ABNT 1045", "tratamento": "Indução", "dureza": "35 a 50 HRc, mínimo 0,5 mm abaixo da raíz do dente", "acabamento": "Pintura preta", "pesoLiquido(Kg)": "2,5370", "pesoBruto(Kg)": "2,5370"},{"_id:": 100114621, "nome:": "Reparo do dedo retrátil - 0877-00", "descricao": "Reparo do dedo retrátil", "linha": "Plataforma", "familia": "Dedo retrátil", "aplicacao": "Sem fim alimentação", "material": "Aço ABNT 1010 (parafusos sextavados, esfera nylon)", "tratamento": "Cementação", "dureza": "mínimo 75 HR15N", "acabamento": "Bicromatizado", "pesoLiquido(Kg)": "0,1700", "pesoBruto(Kg)": "0,1700"},{"_id:": 100237153, "nome:": "Barra de corte - 0752-00", "descricao": "Barra de corte", "atributos": "16\", sem cabeça", "observacoes": "Lâmina 0231-00 (vazada)", "linha": "Plataforma", "familia": "Barra de corte", "aplicacao": "Sistema de corte", "material": "Base: Trefilado ABNT 1045", "tratamento": "65% encruamento", "acabamento": "Pintura preta", "pesoLiquido(Kg)": "9,4500", "pesoBruto(Kg)": "9,4500"},{"_id:": 100409253, "nome:": "Braço - 0077-00", "descricao": "Braço", "observacoes": "Caixa 0433-00", "linha": "Plataforma", "familia": "Braço", "aplicacao": "Acionamento navalha", "material": "Ferro fundido nodular GGG60", "acabamento": "Pintura amarela", "pesoLiquido(Kg)": "1,6500", "pesoBruto(Kg)": "1,6500"},{"_id:": 101280639, "nome:": "Engrenagem - 0207-00", "descricao": "Engrenagem", "atributos": "Z10 P 41,40 mm", "linha": "Colheitadeira", "familia": "Engrenagem", "aplicacao": "Elevador de palha", "material": "Ferro fundido cinzento GG25", "tratamento": "Indução", "dureza": "40 a 50 HRc, região dos dentes, profundidade 2 a 5 mm", "acabamento": "Pintura amarela", "pesoLiquido(Kg)": "1,4870", "pesoBruto(Kg)": "1,4970"},{"_id:": 101284989, "nome:": "Barra flexível porta dedos - 0342-01", "descricao": "Barra flexível porta dedos", "atributos": "13\", furo Ø 8 mm", "linha": "Plataforma", "familia": "Régua", "aplicacao": "Sistema de corte", "material": "Aço ABNT 1070", "dureza": "30 a 36 HRc", "acabamento": "Pintura amarela", "pesoLiquido(Kg)": "9,8760", "pesoBruto(Kg)": "9,8760"},{"_id:": 101277738, "nome:": "Cabeça da navalha - 0300-01", "descricao": "Cabeça da navalha", "atributos": "Furo Ø 5,5 mm", "linha": "Plataforma", "familia": "Cabeça da navalha", "aplicacao": "Sistema de corte", "material": "Ferro fundido nodular GGG40, haste: aço ABNT 1045", "acabamento": "Pintura verde", "pesoLiquido(Kg)": "1,6290", "pesoBruto(Kg)": "1,6290"},{"_id:": 100161205, "nome:": "Barra de corte - 0116-01", "descricao": "Barra de corte", "atributos": "16\", sem cabeça, parafusada", "observacoes": "Lâmina 0106-01 (vazada e serrilhado fino)", "linha": "Plataforma", "familia": "Barra de corte", "aplicacao": "Sistema de corte longo", "material": "Base: Trefilado ABNT 1045", "tratamento": "65% encruamento", "acabamento": "Pintura verde", "pesoLiquido(Kg)": "9,3800", "pesoBruto(Kg)": "9,3800"},{"_id:": 100886429, "nome:": "Barra de corte - 3466-00", "descricao": "Barra de corte", "atributos": "35\", sem cabeça, esq.", "observacoes": "Lâminas 3468-00/3469-00/3471-00", "linha": "Plataforma", "familia": "Barra de corte", "aplicacao": "Sistema de corte", "material": "Base: Trefilado ABNT 1045", "tratamento": "65% encruamento", "acabamento": "Pintura preta", "pesoLiquido(Kg)": "12,7120", "pesoBruto(Kg)": "12,7120"},{"_id:": 101297217, "nome:": "Dedo retrátil - 0653-01", "descricao": "Dedo retrátil", "atributos": "Furo Ø 5 mm", "linha": "Plataforma", "familia": "Dedo retrátil", "aplicacao": "Sem fim alimentação", "material": "Aço ABNT 1045", "tratamento": "Indução", "dureza": "mínimo 52 HRc", "acabamento": "Oleado", "pesoLiquido(Kg)": "0,3870", "pesoBruto(Kg)": "0,3890"},{"_id:": 101285030, "nome:": "Barra flexível porta dedos - 0345-01", "descricao": "Barra flexível porta dedos", "atributos": "19\", furo Ø 8 mm", "linha": "Plataforma", "familia": "Régua", "aplicacao": "Sistema de corte", "material": "Aço ABNT 1070", "dureza": "30 a 36 HRc", "acabamento": "Pintura amarela", "pesoLiquido(Kg)": "15,0400", "pesoBruto(Kg)": "15,0400"},{"_id:": 101297255, "nome:": "Apertador da navalha - 0818-02", "descricao": "Apertador da navalha", "atributos": "Furo Ø 8 mm", "linha": "Plataforma", "familia": "Proteção da faca", "aplicacao": "Sistema de corte curto", "material": "Ferro fundido nodular GGG60", "tratamento": "Indução", "dureza": "mínimo 55 HRc", "acabamento": "Pintura preta", "pesoLiquido(Kg)": "0,3790", "pesoBruto(Kg)": "0,3790"},{"_id:": 101277974, "nome:": "Luva estriada - 3191-00", "descricao": "Luva estriada", "linha": "Colheitadeira", "familia": "Bucha", "aplicacao": "Tração", "material": "Aço ABNT 8620", "tratamento": "Cementação", "dureza": "55 a 58 HRc", "acabamento": "Oleado", "pesoLiquido(Kg)": "0,7750", "pesoBruto(Kg)": "0,7850"},{"_id:": 101296975, "nome:": "Lâmina dupla - 0081-01", "descricao": "Lâmina dupla", "atributos": "Dente fino, 4 furos Ø 6,3 mm liso", "linha": "Plataforma", "familia": "Lâmina de corte", "aplicacao": "Sistema de corte curto", "material": "Aço ABNT 1075", "tratamento": "Austêmpera", "dureza": "mínimo 54 HRc", "acabamento": "Envernizado", "pesoLiquido(Kg)": "0,1050", "pesoBruto(Kg)": "0,1050"},{"_id:": 100018295, "nome:": "Barra de corte - 0654-01", "descricao": "Barra de corte", "atributos": "14\", sem cabeça, rebitada", "observacoes": "Lâmina 0697-00", "linha": "Plataforma", "familia": "Barra de corte", "aplicacao": "Sistema de corte", "material": "Base: Trefilado ABNT 1045", "tratamento": "65% encruamento", "acabamento": "Pintura preta", "pesoLiquido(Kg)": "8,9700", "pesoBruto(Kg)": "8,9700"},{"_id:": 102697870, "nome:": "Junção da barra seccionada - 6300-99", "descricao": "Junção da barra seccionada", "linha": "Plataforma", "familia": "Junção da barra seccionada", "aplicacao": "Sistema de corte", "material": "Barra reforço: Aço ABNT 1070", "tratamento": "Tempera", "dureza": "47 a 52 HRc", "acabamento": "Envernizado", "pesoLiquido(Kg)": "0,5260", "pesoBruto(Kg)": "0,5260"},{"_id:": 101297453, "nome:": "Polia - 3393-00", "descricao": "Polia", "atributos": "Balanceada individualmente", "linha": "Colheitadeira", "familia": "Polia", "aplicacao": "Bomba hidráulica", "material": "Ferro fundido cinzento GG25", "acabamento": "Pintura preta", "pesoLiquido(Kg)": "14,7450", "pesoBruto(Kg)": "14,7450"},{"_id:": 100248692, "nome:": "Barra de corte - 0714-01", "descricao": "Barra de corte", "atributos": "14\", sem cabeça, parafusada", "observacoes": "Lâmina 0700-01", "linha": "Plataforma", "familia": "Barra de corte", "aplicacao": "Sistema de corte longo", "material": "Base: Trefilado ABNT 1045", "tratamento": "65% encruamento", "acabamento": "Pintura verde", "pesoLiquido(Kg)": "8,2500", "pesoBruto(Kg)": "8,2500"},,{"_id:": 100024067, "nome:": "Colar - 0142-00", "descricao": "Colar", "linha": "Trator", "familia": "Embreagem", "aplicacao": "Embreagem", "material": "Ferro fundido cinzento GG15", "acabamento": "Oleado", "pesoLiquido(Kg)": "0,4220", "pesoBruto(Kg)": "0,4680"},{"_id:": 100696028, "nome:": "Dedo duplo longo - 3764-00", "descricao": "Dedo duplo longo", "atributos": "Fundido, furo Ø 10 mm", "observacoes": "", "linha": "Plataforma", "familia": "Proteção da faca", "aplicacao": "Sistema de corte longo", "material": "Ferro fundido nodular GGG60", "tratamento": "Indução", "dureza": "mínimo 55 HRc", "acabamento": "Pintura preta", "pesoLiquido(Kg)": "0,8740", "pesoBruto(Kg)": "0,8740"},{"_id:": 101277356, "nome:": "Mancal - 0103-00", "descricao": "Mancal", "linha": "Plataforma", "familia": "Mancal", "aplicacao": "Acionamento navalha", "material": "Ferro fundido nodular GGG40", "acabamento": "Oleado", "pesoLiquido(Kg)": "1,5000", "pesoBruto(Kg)": "1,5050"},{"_id:": 101297309, "nome:": "Meia polia - 3024-00", "descricao": "Meia polia", "atributos": "Furo para eixo de 45 mm", "linha": "Colheitadeira", "familia": "Meia Polia", "aplicacao": "Cilindro batedor", "material": "Ferro fundido cinzento GG25", "tratamento": "Indução", "acabamento": "Pintura preta", "pesoLiquido(Kg)": "22,5000", "pesoBruto(Kg)": "24,5000"},{"_id:": 102194232, "nome:": "Barra de corte seccionada - 6840-00", "descricao": "Barra de corte seccionada", "atributos": "40\", sem cabeça", "observacoes": "Lâmina 3472-00", "linha": "Plataforma", "familia": "Barra de corte seccionada", "aplicacao": "Sistema de corte", "material": "Base: Trefilado ABNT 1045", "tratamento": "65% encruamento", "acabamento": "Pintura preta", "pesoLiquido(Kg)": "30,0000", "pesoBruto(Kg)": "30,0000"},{"_id:": 100792911, "nome:": "Barra flexível porta dedos - 3286-00", "descricao": "Barra flexível porta dedos", "atributos": "20\", furo Ø 10 mm", "linha": "Plataforma", "familia": "Régua", "aplicacao": "Sistema de corte", "material": "Aço ABNT 1075", "dureza": "30 a 36 HRc", "acabamento": "Pintura verde", "pesoLiquido(Kg)": "18,0000", "pesoBruto(Kg)": "18,6420"},{"_id:": 100369762, "nome:": "Barra de corte seccionada - 6425-00", "descricao": "Barra de corte seccionada", "atributos": "25\", sem cabeça", "observacoes": "Lâmina 0910-01, substitui 3182-00", "linha": "Plataforma", "familia": "Barra de corte seccionada", "aplicacao": "Sistema de corte", "material": "Base: Trefilado ABNT 1045", "tratamento": "65% encruamento", "acabamento": "Pintura preta", "pesoLiquido(Kg)": "14,8500", "pesoBruto(Kg)": "14,8500"},{"_id:": 100102123, "nome:": "Pistão - 3168-00", "descricao": "Pistão", "linha": "Trator", "familia": "Hidráulico", "aplicacao": "Bomba hidráulica", "material": "Ferro fundido nodular GGG50", "acabamento": "Oleado", "pesoLiquido(Kg)": "0,7030", "pesoBruto(Kg)": "0,7130"},{"_id:": 100415803, "nome:": "Engrenagem - 3463-00", "descricao": "Engrenagem", "atributos": "Z13 P 41,4 mm", "linha": "Colheitadeira", "familia": "Engrenagem", "aplicacao": "Elevador de palha", "material": "Ferro fundido cinzento GG25", "tratamento": "Indução", "dureza": "40 a 50 HRc", "acabamento": "Pintura verde", "pesoLiquido(Kg)": "5,2650", "pesoBruto(Kg)": "5,2650"},{"_id:": 100373899, "nome:": "Barra de corte seccionada - 6040-00", "descricao": "Barra de corte seccionada", "atributos": "20\", sem cabeça", "observacoes": "Lâmina 0106-01, substitui 3126-00", "linha": "Plataforma", "familia": "Barra de corte seccionada", "aplicacao": "Sistema de corte longo", "material": "Base: Trefilado ABNT 1045", "tratamento": "65% encruamento", "acabamento": "Pintura verde", "pesoLiquido(Kg)": "13,0050", "pesoBruto(Kg)": "13,0050"},{"_id:": 101297279, "nome:": "Apertador da navalha - 0820-02", "descricao": "Apertador da navalha", "atributos": "Furo Ø 8 mm, esq.", "observacoes": "", "linha": "Plataforma", "familia": "Proteção da faca", "aplicacao": "Sistema de corte curto", "material": "Ferro fundido nodular GGG60", "tratamento": "Indução", "dureza": "mínimo 55 HRc", "acabamento": "Pintura preta", "pesoLiquido(Kg)": "0,4160", "pesoBruto(Kg)": "0,4160"},{"_id:": 101296951, "nome:": "Faca - 0061-01", "descricao": "Faca", "atributos": "Furo Ø 18 mm", "linha": "Colheitadeira", "familia": "Faca do picador", "aplicacao": "Picador de palha", "material": "Aço ABNT 1070", "tratamento": "Indução", "dureza": "52 a 62 HRc (corte) 15 a 25 HRc restante da faca", "acabamento": "Pintura preta", "pesoLiquido(Kg)": "0,3220", "pesoBruto(Kg)": "0,3220"},{"_id:": 102390443, "nome:": "Parafuso - 0741-00", "descricao": "Parafuso", "atributos": "M6 x 20 mm, oblongo", "observacoes": "Sistema 4\"", "linha": "Plataforma", "familia": "Parafuso - Porca - Rebite", "aplicacao": "Sistema de corte curto", "material": "Qualidade 10.9", "acabamento": "Bicromatizado", "pesoLiquido(Kg)": "0,6670", "pesoBruto(Kg)": "0,6670"},{"_id:": 100227031, "nome:": "Barra de corte - 0751-00", "descricao": "Barra de corte", "atributos": "14\", sem cabeça", "observacoes": "Lâmina 0231-00 (vazada)", "linha": "Plataforma", "familia": "Barra de corte", "aplicacao": "Sistema de corte", "material": "Base: Trefilado ABNT 1045", "tratamento": "65% encruamento", "acabamento": "Pintura preta", "pesoLiquido(Kg)": "8,2680", "pesoBruto(Kg)": "8,2680"},{"_id:": 101286914, "nome:": "Engrenagem - 0079-00", "descricao": "Engrenagem", "atributos": "Z21 P 1/2\"", "linha": "Colheitadeira", "familia": "Engrenagem", "aplicacao": "Descarga", "material": "Ferro fundido nodular GGG60", "tratamento": "Indução", "dureza": "mínimo 38 HRc, região dos dentes, profundidade de 1 a 3 mm", "acabamento": "Pintura preta", "pesoLiquido(Kg)": "0,3100", "pesoBruto(Kg)": "0,3150"},{"_id:": 100649703, "nome:": "Bucha da faca - 0271-00", "descricao": "Bucha da faca", "observacoes": "Faca com furo Ø 25 mm e espressura 5 mm (0352-00)", "linha": "Colheitadeira", "familia": "Bucha", "aplicacao": "Picador de palha", "material": "Aço ABNT 1213", "tratamento": "Cementação", "dureza": "mínimo 55 HRc, profundidade 0,5 a 0,7 mm", "acabamento": "Oleado", "pesoLiquido(Kg)": "0,1770", "pesoBruto(Kg)": "0,1770"},{"_id:": 100409123, "nome:": "Polia - 3394-00", "descricao": "Polia", "atributos": "Balanceada individualmente", "linha": "Colheitadeira", "familia": "Polia", "aplicacao": "Elevador de palha", "material": "Ferro fundido cinzento GG25", "acabamento": "Pintura preta", "pesoLiquido(Kg)": "16,1400", "pesoBruto(Kg)": "16,1400"},{"_id:": 101297101, "nome:": "Dedo retrátil - 0279-01", "descricao": "Dedo retrátil", "atributos": "Furo Ø 4 mm", "observacoes": "Pino R", "linha": "Plataforma", "familia": "Dedo retrátil", "aplicacao": "Sem fim alimentação", "material": "Aço ABNT 1045", "tratamento": "Indução", "dureza": "mínimo 52 HRc", "acabamento": "Oleado", "pesoLiquido(Kg)": "0,4300", "pesoBruto(Kg)": "0,4300"},{"_id:": 100018325, "nome:": "Barra de corte - 0316-01", "descricao": "Barra de corte", "atributos": "16\", sem cabeça, rebitada", "observacoes": "Lâmina 0185-01", "linha": "Plataforma", "familia": "Barra de corte", "aplicacao": "Sistema de corte longo", "material": "Base: Trefilado ABNT 1045", "tratamento": "65% encruamento", "acabamento": "Pintura verde", "pesoLiquido(Kg)": "10,2950", "pesoBruto(Kg)": "10,2950"},{"_id:": 101296920, "nome:": "Bucha da faca - 0025-00", "descricao": "Bucha da faca", "observacoes": "Faca com furo Ø 25 mm e espressura 3 mm (0009-00/0028-00)", "linha": "Colheitadeira", "familia": "Bucha", "aplicacao": "Picador de palha", "material": "Aço ABNT 1213", "tratamento": "Cementação", "dureza": "85 a 88 HRc, profundidade 0,2 a 0,3 mm", "acabamento": "Oleado", "pesoLiquido(Kg)": "0,0110", "pesoBruto(Kg)": "0,0110"},{"_id:": 100018318, "nome:": "Barra de corte - 0398-01", "descricao": "Barra de corte", "atributos": "15\", sem cabeça, rebitada", "observacoes": "Lâmina 0415-01", "linha": "Plataforma", "familia": "Barra de corte", "aplicacao": "Sistema de corte", "material": "Base: Trefilado ABNT 1045", "tratamento": "65% encruamento", "acabamento": "Pintura preta", "pesoLiquido(Kg)": "9,2460", "pesoBruto(Kg)": "9,2460"},{"_id:": 104428205, "nome:": "Barra flexível porta dedos - 3407-01", "descricao": "Barra flexível porta dedos", "atributos": "35\" furo Ø 10 mm, esq.", "linha": "Plataforma", "familia": "Régua", "aplicacao": "Sistema de corte", "material": "Aço ABNT 1070", "dureza": "30 a 36 HRc", "acabamento": "Pintura preta", "pesoLiquido(Kg)": "14,5000", "pesoBruto(Kg)": "15,0230"},{"_id:": 100236118, "nome:": "Lâmina de Corte - 0056-01", "descricao": "Lâmina de Corte", "atributos": "Dente grosso, furo Ø 5,5 mm liso", "observacoes": "Parafuso 0690-00", "linha": "Plataforma", "familia": "Lâmina de corte", "aplicacao": "Sistema de corte", "material": "Aço ABNT 1070", "tratamento": "Indução", "dureza": "mínimo 54 HRc", "acabamento": "Envernizado", "pesoLiquido(Kg)": "0,0840", "pesoBruto(Kg)": "0,0840"},{"_id:": 101284927, "nome:": "Disco - 0052-00", "descricao": "Disco", "linha": "Colheitadeira", "familia": "Variador de velocidade", "aplicacao": "Ventilador", "material": "Aço ABNT 1020", "acabamento": "Pintura amarela", "pesoLiquido(Kg)": "1,0740", "pesoBruto(Kg)": "1,0790"},{"_id:": 101287508, "nome:": "Barra flexível porta dedos - 0441-00", "descricao": "Barra flexível porta dedos", "atributos": "23\", furo Ø 10 mm", "linha": "Plataforma", "familia": "Régua", "aplicacao": "Sistema de corte", "material": "Aço ABNT 1075", "dureza": "30 a 36 HRc", "acabamento": "Pintura verde", "pesoLiquido(Kg)": "20,2800", "pesoBruto(Kg)": "20,2800"},{"_id:": 101296838, "nome:": "Dedo duplo longo - 0003-01", "descricao": "Dedo duplo longo", "atributos": "Furo Ø 10 mm", "observacoes": "", "linha": "Plataforma", "familia": "Proteção da faca", "aplicacao": "Sistema de corte longo", "material": "Ferro fundido nodular GGG60", "tratamento": "Indução", "dureza": "mínimo 55 HRc", "acabamento": "Pintura preta", "pesoLiquido(Kg)": "1,0870", "pesoBruto(Kg)": "1,0870"},{"_id:": 101280745, "nome:": "Engrenagem - 0100-00", "descricao": "Engrenagem", "atributos": "Z10 P 41,4 mm", "linha": "Colheitadeira", "familia": "Engrenagem", "aplicacao": "Elevador de palha", "material": "Ferro fundido cinzento GG20", "tratamento": "Indução", "dureza": "40 a 50 HRc", "acabamento": "Pintura verde", "pesoLiquido(Kg)": "1,8070", "pesoBruto(Kg)": "1,8170"},{"_id:": 101280813, "nome:": "Engrenagem - 0835-00", "descricao": "Engrenagem", "atributos": "Z48 P 5/8\"", "linha": "Colheitadeira", "familia": "Engrenagem", "aplicacao": "Cilindro batedor", "material": "Ferro fundido nodular GGG50", "tratamento": "Indução", "dureza": "38 a 45 HRc", "acabamento": "Pintura verde", "pesoLiquido(Kg)": "3,4430", "pesoBruto(Kg)": "3,4530"},{"_id:": 100143515, "nome:": "Barra de corte - 0913-01", "descricao": "Barra de corte", "atributos": "13\", sem cabeça, rebitada", "observacoes": "Lâmina 0912-01 (vazada)", "linha": "Plataforma", "familia": "Barra de corte", "aplicacao": "Sistema de corte longo", "material": "Base: Trefilado ABNT 1045", "tratamento": "65% encruamento", "acabamento": "Pintura verde", "pesoLiquido(Kg)": "7,2380", "pesoBruto(Kg)": "7,2380"},{"_id:": 101296968, "nome:": "Faca Fixa *U* - 0069-00", "descricao": "Faca Fixa *U*", "linha": "Colheitadeira", "familia": "Faca do picador", "aplicacao": "Picador de palha", "material": "Aço-cromo-vanádio ABNT 6158", "tratamento": "Indução", "dureza": "mínimo 52 HRc", "acabamento": "Oleado", "pesoLiquido(Kg)": "0,4150", "pesoBruto(Kg)": "0,4250"},{"_id:": 101297286, "nome:": "Dedo duplo curto - 0821-02", "descricao": "Dedo duplo curto", "atributos": "Furo Ø 8 mm", "observacoes": "", "linha": "Plataforma", "familia": "Proteção da faca", "aplicacao": "Sistema de corte curto", "material": "Ferro fundido nodular GGG60", "tratamento": "Indução", "dureza": "mínimo 55 HRc", "acabamento": "Pintura preta", "pesoLiquido(Kg)": "0,4580", "pesoBruto(Kg)": "0,4580"},{"_id:": 100023831, "nome:": "Braço - 0355-00", "descricao": "Braço", "observacoes": "4x2", "linha": "Trator", "familia": "Direção", "aplicacao": "Eixo dianteiro (direção)", "material": "Ferro fundido nodular GGG50 com bucha de bronze", "acabamento": "Pintura preta", "pesoLiquido(Kg)": "2,7570", "pesoBruto(Kg)": "2,7570"},{"_id:": 100021257, "nome:": "Catraca - 0382-00", "descricao": "Catraca", "linha": "Colheitadeira", "familia": "Catraca", "aplicacao": "Elevador de palha", "material": "Ferro fundido nodular GGG50", "tratamento": "Revenimento", "dureza": "40 a 50 HRc", "acabamento": "Pintura amarela", "pesoLiquido(Kg)": "0,2470", "pesoBruto(Kg)": "0,2470"},{"_id:": 101276915, "nome:": "Eixo - 0489-00", "descricao": "Eixo", "linha": "Colheitadeira", "familia": "Eixo", "aplicacao": "Tomada de força (PTO)", "material": "Aço ABNT 8640", "tratamento": "Indução", "dureza": "45 a 55 HRc, na região estriada, profundidade 1,5 a 3,5 mm", "acabamento": "Oleado", "pesoLiquido(Kg)": "4,9390", "pesoBruto(Kg)": "4,9490"},{"_id:": 101280646, "nome:": "Engrenagem - 0170-01", "descricao": "Engrenagem", "atributos": "Z10 P 41,40 mm", "linha": "Colheitadeira", "familia": "Engrenagem", "aplicacao": "Elevador de palha", "material": "Ferro fundido cinzento GG25", "tratamento": "Indução", "dureza": "40 a 50 HRc, região dos dentes, profundidade 2 a 5 mm", "acabamento": "Pintura preta", "pesoLiquido(Kg)": "1,5780", "pesoBruto(Kg)": "1,5830"},{"_id:": 100356533, "nome:": "Barra de corte seccionada - 6225-00", "descricao": "Barra de corte seccionada", "atributos": "25\", sem cabeça", "observacoes": "Lâmina 0082-01 (grossa), sistema 4\"", "linha": "Plataforma", "familia": "Barra de corte seccionada", "aplicacao": "Sistema de corte curto", "material": "Base: Trefilado ABNT 1045", "tratamento": "65% encruamento", "acabamento": "Pintura verde", "pesoLiquido(Kg)": "17,0000", "pesoBruto(Kg)": "17,0000"},{"_id:": 100102789, "nome:": "Lâmina de corte - 0910-01", "descricao": "Lâmina de corte", "atributos": "Dente grosso, furo Ø 6,5mm quadrado", "observacoes": "Parafuso 0853-00", "linha": "Plataforma", "familia": "Lâmina de corte", "aplicacao": "Sistema de corte", "material": "Aço ABNT 1070", "tratamento": "Indução", "dureza": "mínimo 54 HRc", "acabamento": "Envernizado", "pesoLiquido(Kg)": "0,0640", "pesoBruto(Kg)": "0,0640"},{"_id:": 101292816, "nome:": "Barra flexível porta dedos - 0330-00", "descricao": "Barra flexível porta dedos", "atributos": "14\", furo Ø 10 mm", "observacoes": "Navalha rebitada", "linha": "Plataforma", "familia": "Régua", "aplicacao": "Sistema de corte", "material": "Aço ABNT 1060", "acabamento": "Pintura preta", "pesoLiquido(Kg)": "15,5750", "pesoBruto(Kg)": "15,5750"},{"_id:": 100110777, "nome:": "Engrenagem - 0347-01", "descricao": "Engrenagem", "atributos": "Z10 P 41,40 mm", "linha": "Colheitadeira", "familia": "Engrenagem", "aplicacao": "Elevador de palha", "material": "Ferro fundido nodular GGG60", "tratamento": "Indução", "dureza": "40 a 50 HRc, região dos dentes, profundidade 2 a 5 mm", "acabamento": "Pintura amarela", "pesoLiquido(Kg)": "1,7370", "pesoBruto(Kg)": "1,7370"},{"_id:": 101297415, "nome:": "Guia - 3240-00", "descricao": "Guia", "atributos": "Superior, com parafuso de regulagem", "observacoes": "Sistema 4\"", "linha": "Plataforma", "familia": "Proteção da faca", "aplicacao": "Sistema de corte curto", "material": "Ferro fundido nodular GGG50", "acabamento": "Pintura preta", "pesoLiquido(Kg)": "0,2800", "pesoBruto(Kg)": "0,2800"},{"_id:": 101276083, "nome:": "Eixo - 0952-00", "descricao": "Eixo", "linha": "Colheitadeira", "familia": "Eixo", "aplicacao": "Elevador de grãos", "material": "Aço ABNT 1020", "acabamento": "Oleado", "pesoLiquido(Kg)": "0,7830", "pesoBruto(Kg)": "0,7880"},{"_id:": 100207200, "nome:": "Barra flexível porta dedos - 0344-01", "descricao": "Barra flexível porta dedos", "atributos": "17\", furo Ø 8 mm", "linha": "Plataforma", "familia": "Régua", "aplicacao": "Sistema de corte", "material": "Aço ABNT 1070", "dureza": "30 a 36 HRc", "acabamento": "Pintura amarela", "pesoLiquido(Kg)": "13,5300", "pesoBruto(Kg)": "13,5300"},{"_id:": 103809685, "nome:": "Dedo duplo curto - 3427-01", "descricao": "Dedo duplo curto", "atributos": "Furo Ø 10 mm", "observacoes": "2 por pé", "linha": "Plataforma", "familia": "Proteção da faca", "aplicacao": "Sistema de corte curto", "material": "Ferro fundido nodular GGG60", "tratamento": "Indução", "dureza": "mínimo 55 HRc", "acabamento": "Pintura preta", "pesoLiquido(Kg)": "0,3940", "pesoBruto(Kg)": "0,3940"},,{"_id:": 101297477, "nome:": "Polia - 3398-00", "descricao": "Polia", "atributos": "Balanceada individualmente", "linha": "Colheitadeira", "familia": "Polia", "aplicacao": "Acionamento principal", "material": "Ferro fundido cinzento GG25", "acabamento": "Pintura preta", "pesoLiquido(Kg)": "22,5000", "pesoBruto(Kg)": "23,1660"},{"_id:": 101281988, "nome:": "Polia - 0416-00", "descricao": "Polia", "linha": "Colheitadeira", "familia": "Variador de velocidade", "aplicacao": "Ventilador", "material": "Ferro fundido cinzento GG20", "acabamento": "Pintura verde", "pesoLiquido(Kg)": "1,8510", "pesoBruto(Kg)": "1,8680"},{"_id:": 100024241, "nome:": "Engrenagem - 0869-01", "descricao": "Engrenagem", "atributos": "Z19 P 41,4 mm", "linha": "Colheitadeira", "familia": "Engrenagem", "aplicacao": "Elevador de palha", "material": "Ferro fundido nodular GGG60", "tratamento": "Indução", "dureza": "45 a 55 HRc, região dos dentes, profundidade 3 a 6 mm", "acabamento": "Pintura preta", "pesoLiquido(Kg)": "4,7560", "pesoBruto(Kg)": "4,7660"},{"_id:": 101281919, "nome:": "Cubo - 0007-00", "descricao": "Cubo", "linha": "Colheitadeira", "familia": "Cubo", "aplicacao": "Elevador de palha", "material": "Ferro fundido cinzento GG20", "acabamento": "Pintura amarela", "pesoLiquido(Kg)": "1,7420", "pesoBruto(Kg)": "1,7470"},{"_id:": 100017236, "nome:": "Lâmina de corte - 0185-00", "descricao": "Lâmina de corte", "atributos": "Dente fino, furo Ø 5,5 mm liso", "observacoes": "", "linha": "Plataforma", "familia": "Lâmina de corte", "aplicacao": "Sistema de corte", "material": "Aço ABNT 1070", "tratamento": "Indução", "dureza": "mínimo 54 HRc", "acabamento": "Envernizado", "pesoLiquido(Kg)": "0,0870", "pesoBruto(Kg)": "0,0870"},{"_id:": 100839845, "nome:": "Lâmina de corte - 3471-00", "descricao": "Lâmina de corte", "atributos": "Dente grosso, furo Ø 6,5 mm escareado", "observacoes": "Parafuso 0629-00", "linha": "Plataforma", "familia": "Lâmina de corte", "aplicacao": "Sistema de corte", "material": "Aço ABNT 1070", "tratamento": "Indução", "dureza": "mínimo 54 HRc", "acabamento": "Envernizado", "pesoLiquido(Kg)": "0,0900", "pesoBruto(Kg)": "0,0900"},{"_id:": 102390344, "nome:": "Apertador da navalha - 3872-00", "descricao": "Apertador da navalha", "linha": "Plataforma", "familia": "Proteção da faca", "aplicacao": "Sistema de corte curto", "material": "Ferro fundido nodular GGG50", "tratamento": "Indução", "dureza": "mínimo 55 HRc", "acabamento": "Pintura preta", "pesoLiquido(Kg)": "0,6760", "pesoBruto(Kg)": "0,6760"},{"_id:": 100089837, "nome:": "Barra de corte - 0503-01", "descricao": "Barra de corte", "atributos": "13\", sem cabeça", "observacoes": "Lâmina 0910-01", "linha": "Plataforma", "familia": "Barra de corte", "aplicacao": "Sistema de corte", "material": "Base: Trefilado ABNT 1045", "tratamento": "65% encruamento", "acabamento": "Pintura preta", "pesoLiquido(Kg)": "7,3800", "pesoBruto(Kg)": "7,3800"},{"_id:": 100310313, "nome:": "Barra de corte seccionada - 6023-00", "descricao": "Barra de corte seccionada", "atributos": "23\", sem cabeça", "observacoes": "Lâmina 0106-01, substitui 0123-01", "linha": "Plataforma", "familia": "Barra de corte seccionada", "aplicacao": "Sistema de corte longo", "material": "Base: Trefilado ABNT 1045", "tratamento": "65% encruamento", "acabamento": "Pintura verde", "pesoLiquido(Kg)": "14,6140", "pesoBruto(Kg)": "14,6140"},{"_id:": 100091151, "nome:": "Barra de corte - 0613-01", "descricao": "Barra de corte", "atributos": "15\", sem cabeça", "observacoes": "Lâmina 0601-01", "linha": "Plataforma", "familia": "Barra de corte", "aplicacao": "Sistema de corte", "material": "Base: Trefilado ABNT 1045", "tratamento": "65% encruamento", "acabamento": "Pintura preta", "pesoLiquido(Kg)": "9,9000", "pesoBruto(Kg)": "9,9000"},{"_id:": 100094138, "nome:": "Mancal - 0485-00", "descricao": "Mancal", "linha": "Colheitadeira", "familia": "Mancal", "aplicacao": "Peneiras", "material": "Ferro fundido nodular GGG40 (100% ferrítico)", "acabamento": "Bicromatizado", "pesoLiquido(Kg)": "0,2000", "pesoBruto(Kg)": "0,2000"},{"_id:": 101279664, "nome:": "Engrenagem - 0460-00", "descricao": "Engrenagem", "atributos": "Z24 P 5/8\"", "linha": "Colheitadeira", "familia": "Engrenagem", "aplicacao": "Elevador de grãos", "material": "Aço ABNT 1045", "tratamento": "Indução", "dureza": "35 a 50 HRc, mínimo 0,5 mm abaixo da raíz do dente", "acabamento": "Pintura preta", "pesoLiquido(Kg)": "0,7900", "pesoBruto(Kg)": "0,7900"},{"_id:": 101297125, "nome:": "Conjunto facas - 0352-00", "descricao": "Conjunto facas", "atributos": "Furo Ø 25 mm, espessura 5 mm", "observacoes": "3 facas, 3 porcas e 3 buchas", "linha": "Colheitadeira", "familia": "Faca do picador", "aplicacao": "Picador de palha", "material": "Aço ABNT 1070", "tratamento": "Indução", "dureza": "56 a 62 HRc", "acabamento": "Oleado", "pesoLiquido(Kg)": "0,9200", "pesoBruto(Kg)": "0,9300"},{"_id:": 101280769, "nome:": "Engrenagem - 0240-00", "descricao": "Engrenagem", "atributos": "Z13 P 41,4 mm", "linha": "Colheitadeira", "familia": "Engrenagem", "aplicacao": "Elevador de palha", "material": "Ferro fundido cinzento GG25", "tratamento": "Indução", "dureza": "40 a 50 HRc", "acabamento": "Pintura verde", "pesoLiquido(Kg)": "3,3200", "pesoBruto(Kg)": "3,3200"}]